dictionary/__init__.py
dictionary/dictionary.py
cs453_ck_dictionary_2-2.0.0.dist-info/METADATA
cs453_ck_dictionary_2-2.0.0.dist-info/WHEEL
cs453_ck_dictionary_2-2.0.0.dist-info/top_level.txt
cs453_ck_dictionary_2-2.0.0.dist-info/RECORD
