Metadata-Version: 2.1
Name: cs453-ck-dictionary-2
Version: 2.0.0
Summary: UNKNOWN
Author: Cankat Anday Kadim
License: UNKNOWN
Platform: UNKNOWN
Requires-Python: >=3.8
Requires-Dist: requests (>=2.23.0)
